nwp500/__init__.py
nwp500/api_client.py
nwp500/auth.py
nwp500/command_decorators.py
nwp500/config.py
nwp500/converters.py
nwp500/device_capabilities.py
nwp500/device_info_cache.py
nwp500/encoding.py
nwp500/enums.py
nwp500/events.py
nwp500/exceptions.py
nwp500/factory.py
nwp500/field_factory.py
nwp500/models.py
nwp500/mqtt_events.py
nwp500/py.typed
nwp500/temperature.py
nwp500/topic_builder.py
nwp500/utils.py
nwp500/cli/__init__.py
nwp500/cli/__main__.py
nwp500/cli/commands.py
nwp500/cli/handlers.py
nwp500/cli/monitoring.py
nwp500/cli/output_formatters.py
nwp500/cli/rich_output.py
nwp500/cli/token_storage.py
nwp500/mqtt/__init__.py
nwp500/mqtt/client.py
nwp500/mqtt/command_queue.py
nwp500/mqtt/connection.py
nwp500/mqtt/control.py
nwp500/mqtt/diagnostics.py
nwp500/mqtt/periodic.py
nwp500/mqtt/reconnection.py
nwp500/mqtt/subscriptions.py
nwp500/mqtt/utils.py
nwp500_python-7.2.2.dist-info/licenses/LICENSE.txt
nwp500_python-7.2.2.dist-info/METADATA
nwp500_python-7.2.2.dist-info/WHEEL
nwp500_python-7.2.2.dist-info/entry_points.txt
nwp500_python-7.2.2.dist-info/top_level.txt
nwp500_python-7.2.2.dist-info/RECORD
