Metadata-Version: 2.4
Name: nwp500-python
Version: 7.2.2
Summary: A library for controlling Navien NWP500 Water Heaters via NaviLink
Home-page: https://github.com/eman/nwp500-python
Author: Emmanuel Levijarvi
Author-email: emansl@gmail.com
License: MIT
Project-URL: Documentation, https://nwp500-python.readthedocs.io/en/latest/
Project-URL: Source, https://github.com/eman/nwp500-python
Project-URL: Tracker, https://github.com/eman/nwp500-python/issues
Platform: any
Classifier: Development Status :: 4 - Beta
Classifier: Programming Language :: Python
Classifier: Programming Language :: Python :: 3
Classifier: Programming Language :: Python :: 3.13
Classifier: Programming Language :: Python :: 3 :: Only
Requires-Python: >=3.13
License-File: LICENSE.txt
Requires-Dist: aiohttp>=3.8.0
Requires-Dist: awsiotsdk>=1.27.0
Requires-Dist: pydantic>=2.0.0
Requires-Dist: click>=8.0.0
Provides-Extra: cli
Requires-Dist: rich>=13.0.0; extra == "cli"
Provides-Extra: testing
Requires-Dist: setuptools; extra == "testing"
Requires-Dist: pytest; extra == "testing"
Requires-Dist: pytest-cov; extra == "testing"
Requires-Dist: pytest-asyncio; extra == "testing"
Provides-Extra: dev
Requires-Dist: ruff>=0.1.0; extra == "dev"
Requires-Dist: pyright>=1.1.0; extra == "dev"
Requires-Dist: setuptools; extra == "dev"
Requires-Dist: pytest; extra == "dev"
Requires-Dist: pytest-cov; extra == "dev"
Requires-Dist: pytest-asyncio; extra == "dev"
Dynamic: license-file
